{
  "updated": "2025-12-18 23:21 UTC",
  "data_sources": {
    "usa": "NOHRSC",
    "canada": "Derived (NOHRSC ratio)",
    "rutgers_available": true,
    "copernicus_available": false
  },
  "combined": {
    "cover": 34.5,
    "change": "+4.0%",
    "context": "Approximately 34% of North American land area currently has visible snow cover",
    "temperature": {
      "avg_temp_c": 1.2,
      "avg_temp_f": 34.2,
      "avg_anomaly_c": 1.7,
      "avg_anomaly_f": 3.1
    }
  },
  "usa": {
    "cover": 21.6,
    "change": "+4.0%",
    "areaSqMi": 820152,
    "areaSqKm": 2124185,
    "avgDepthInches": 3,
    "avgDepthCm": 7.6,
    "priorYearAvgDepthInches": 1.3,
    "priorYearAvgDepthCm": 3.3,
    "history": [
      {
        "date": "2025-11-19",
        "value": 9.6
      },
      {
        "date": "2025-11-20",
        "value": 10.5
      },
      {
        "date": "2025-11-21",
        "value": 13.7
      },
      {
        "date": "2025-11-22",
        "value": 11.0
      },
      {
        "date": "2025-11-23",
        "value": 10.4
      },
      {
        "date": "2025-11-24",
        "value": 13.8
      },
      {
        "date": "2025-11-25",
        "value": 14.4
      },
      {
        "date": "2025-11-26",
        "value": 15.0
      },
      {
        "date": "2025-11-27",
        "value": 13.4
      },
      {
        "date": "2025-11-28",
        "value": 12.8
      },
      {
        "date": "2025-11-29",
        "value": 14.6
      },
      {
        "date": "2025-11-30",
        "value": 14.2
      },
      {
        "date": "2025-12-01",
        "value": 13.4
      },
      {
        "date": "2025-12-02",
        "value": 13.8
      },
      {
        "date": "2025-12-03",
        "value": 14.7
      },
      {
        "date": "2025-12-04",
        "value": 14.4
      },
      {
        "date": "2025-12-05",
        "value": 14.6
      },
      {
        "date": "2025-12-06",
        "value": 15.1
      },
      {
        "date": "2025-12-07",
        "value": 16.0
      },
      {
        "date": "2025-12-08",
        "value": 20.2
      },
      {
        "date": "2025-12-09",
        "value": 16.6
      },
      {
        "date": "2025-12-10",
        "value": 16.9
      },
      {
        "date": "2025-12-11",
        "value": 17.6
      },
      {
        "date": "2025-12-12",
        "value": 18.3
      },
      {
        "date": "2025-12-13",
        "value": 18.3
      },
      {
        "date": "2025-12-14",
        "value": 17.7
      },
      {
        "date": "2025-12-15",
        "value": 20.0
      },
      {
        "date": "2025-12-16",
        "value": 20.8
      },
      {
        "date": "2025-12-17",
        "value": 21.4
      },
      {
        "date": "2025-12-18",
        "value": 20.0
      }
    ],
    "priorYearHistory": [
      {
        "date": "2024-11-19",
        "value": 13.6
      },
      {
        "date": "2024-11-20",
        "value": 14.5
      },
      {
        "date": "2024-11-21",
        "value": 14.8
      },
      {
        "date": "2024-11-22",
        "value": 18.6
      },
      {
        "date": "2024-11-23",
        "value": 15.7
      },
      {
        "date": "2024-11-24",
        "value": 15.6
      },
      {
        "date": "2024-11-25",
        "value": 17.1
      },
      {
        "date": "2024-11-26",
        "value": 19.3
      },
      {
        "date": "2024-11-27",
        "value": 21.7
      },
      {
        "date": "2024-11-28",
        "value": 23.5
      },
      {
        "date": "2024-11-29",
        "value": 25.8
      },
      {
        "date": "2024-11-30",
        "value": 25.4
      },
      {
        "date": "2024-12-01",
        "value": 25.7
      },
      {
        "date": "2024-12-02",
        "value": 25.1
      },
      {
        "date": "2024-12-03",
        "value": 24.4
      },
      {
        "date": "2024-12-04",
        "value": 22.7
      },
      {
        "date": "2024-12-05",
        "value": 21.3
      },
      {
        "date": "2024-12-06",
        "value": 21.5
      },
      {
        "date": "2024-12-07",
        "value": 20.3
      },
      {
        "date": "2024-12-08",
        "value": 17.6
      },
      {
        "date": "2024-12-09",
        "value": 16.8
      },
      {
        "date": "2024-12-10",
        "value": 19.2
      },
      {
        "date": "2024-12-11",
        "value": 19.1
      },
      {
        "date": "2024-12-12",
        "value": 21.7
      },
      {
        "date": "2024-12-13",
        "value": 21.1
      },
      {
        "date": "2024-12-14",
        "value": 21.1
      },
      {
        "date": "2024-12-15",
        "value": 23.4
      },
      {
        "date": "2024-12-16",
        "value": 25.2
      },
      {
        "date": "2024-12-17",
        "value": 21.6
      },
      {
        "date": "2024-12-18",
        "value": 20.8
      }
    ],
    "temperature": {
      "avg_temp_c": 5.8,
      "avg_temp_f": 42.4,
      "avg_anomaly_c": 4.2,
      "avg_anomaly_f": 7.5
    }
  },
  "canada": {
    "cover": 47.2,
    "change": "+1.4%",
    "areaSqMi": 1818543,
    "areaSqKm": 4710009,
    "avgDepthInches": 5.9,
    "avgDepthCm": 15,
    "priorYearAvgDepthInches": 2.6,
    "priorYearAvgDepthCm": 6.6,
    "history": [
      {
        "date": "2025-11-19",
        "value": 38.1
      },
      {
        "date": "2025-11-20",
        "value": 40.9
      },
      {
        "date": "2025-11-21",
        "value": 40.7
      },
      {
        "date": "2025-11-22",
        "value": 40.8
      },
      {
        "date": "2025-11-23",
        "value": 40.9
      },
      {
        "date": "2025-11-24",
        "value": 43.3
      },
      {
        "date": "2025-11-25",
        "value": 43.4
      },
      {
        "date": "2025-11-26",
        "value": 41.1
      },
      {
        "date": "2025-11-27",
        "value": 40.3
      },
      {
        "date": "2025-11-28",
        "value": 40.4
      },
      {
        "date": "2025-11-29",
        "value": 41.1
      },
      {
        "date": "2025-11-30",
        "value": 41.9
      },
      {
        "date": "2025-12-01",
        "value": 42.2
      },
      {
        "date": "2025-12-02",
        "value": 42.7
      },
      {
        "date": "2025-12-03",
        "value": 43.7
      },
      {
        "date": "2025-12-04",
        "value": 43.7
      },
      {
        "date": "2025-12-05",
        "value": 42.0
      },
      {
        "date": "2025-12-06",
        "value": 42.1
      },
      {
        "date": "2025-12-07",
        "value": 44.0
      },
      {
        "date": "2025-12-08",
        "value": 45.0
      },
      {
        "date": "2025-12-09",
        "value": 46.4
      },
      {
        "date": "2025-12-10",
        "value": 45.3
      },
      {
        "date": "2025-12-11",
        "value": 45.8
      },
      {
        "date": "2025-12-12",
        "value": 46.5
      },
      {
        "date": "2025-12-13",
        "value": 44.3
      },
      {
        "date": "2025-12-14",
        "value": 44.7
      },
      {
        "date": "2025-12-15",
        "value": 48.7
      },
      {
        "date": "2025-12-16",
        "value": 45.1
      },
      {
        "date": "2025-12-17",
        "value": 47.3
      },
      {
        "date": "2025-12-18",
        "value": 48.6
      }
    ],
    "priorYearHistory": [
      {
        "date": "2024-11-19",
        "value": 54.0
      },
      {
        "date": "2024-11-20",
        "value": 56.5
      },
      {
        "date": "2024-11-21",
        "value": 44.0
      },
      {
        "date": "2024-11-22",
        "value": 69.0
      },
      {
        "date": "2024-11-23",
        "value": 61.7
      },
      {
        "date": "2024-11-24",
        "value": 48.9
      },
      {
        "date": "2024-11-25",
        "value": 51.5
      },
      {
        "date": "2024-11-26",
        "value": 52.9
      },
      {
        "date": "2024-11-27",
        "value": 65.3
      },
      {
        "date": "2024-11-28",
        "value": 74.2
      },
      {
        "date": "2024-11-29",
        "value": 72.6
      },
      {
        "date": "2024-11-30",
        "value": 74.9
      },
      {
        "date": "2024-12-01",
        "value": 80.9
      },
      {
        "date": "2024-12-02",
        "value": 77.7
      },
      {
        "date": "2024-12-03",
        "value": 72.5
      },
      {
        "date": "2024-12-04",
        "value": 68.9
      },
      {
        "date": "2024-12-05",
        "value": 61.3
      },
      {
        "date": "2024-12-06",
        "value": 59.9
      },
      {
        "date": "2024-12-07",
        "value": 55.8
      },
      {
        "date": "2024-12-08",
        "value": 39.2
      },
      {
        "date": "2024-12-09",
        "value": 47.0
      },
      {
        "date": "2024-12-10",
        "value": 51.5
      },
      {
        "date": "2024-12-11",
        "value": 49.7
      },
      {
        "date": "2024-12-12",
        "value": 55.1
      },
      {
        "date": "2024-12-13",
        "value": 51.1
      },
      {
        "date": "2024-12-14",
        "value": 53.3
      },
      {
        "date": "2024-12-15",
        "value": 57.0
      },
      {
        "date": "2024-12-16",
        "value": 54.6
      },
      {
        "date": "2024-12-17",
        "value": 47.7
      },
      {
        "date": "2024-12-18",
        "value": 50.5
      }
    ],
    "temperature": {
      "avg_temp_c": -5.9,
      "avg_temp_f": 21.3,
      "avg_anomaly_c": -2.4,
      "avg_anomaly_f": -4.3
    }
  },
  "metros": [
    {
      "city": "Edmonton",
      "region": "AB",
      "country": "canada",
      "cover": 85,
      "depthInches": 6.2,
      "depthCm": 15.6,
      "trend": "up",
      "history": [
        93.6,
        85.3,
        82.3,
        93.1,
        75.7,
        79.2,
        86.0
      ],
      "temperature": {
        "temp_c": -16.6,
        "temp_f": 2.1,
        "normal_c": -8.1,
        "anomaly_c": -8.5,
        "anomaly_f": -15.3
      },
      "skiMarket": true,
      "priorYearHistory": [
        100,
        100,
        100,
        100,
        100,
        100,
        100
      ]
    },
    {
      "city": "Winnipeg",
      "region": "MB",
      "country": "canada",
      "cover": 65,
      "depthInches": 5.2,
      "depthCm": 13.1,
      "trend": "stable",
      "history": [
        62.1,
        64.5,
        63.1,
        58.6,
        71.4,
        69.8,
        68.3
      ],
      "temperature": {
        "temp_c": -24.9,
        "temp_f": -12.8,
        "normal_c": -9.3,
        "anomaly_c": -15.6,
        "anomaly_f": -28.1
      },
      "skiMarket": false,
      "priorYearHistory": [
        75.9,
        87.6,
        86.0,
        81.1,
        93.9,
        92.2,
        96.5
      ]
    },
    {
      "city": "Quebec City",
      "region": "QC",
      "country": "canada",
      "cover": 65,
      "depthInches": 5.2,
      "depthCm": 13.1,
      "trend": "up",
      "history": [
        71.5,
        67.5,
        62.5,
        61.6,
        75.5,
        64.5,
        71.0
      ],
      "temperature": {
        "temp_c": -6.3,
        "temp_f": 20.7,
        "normal_c": -7.0,
        "anomaly_c": 0.7,
        "anomaly_f": 1.3
      },
      "skiMarket": true,
      "priorYearHistory": [
        100,
        94.8,
        85.2,
        83.3,
        100,
        90.3,
        90.3
      ]
    },
    {
      "city": "Calgary",
      "region": "AB",
      "country": "canada",
      "cover": 60,
      "depthInches": 4.9,
      "depthCm": 12.5,
      "trend": "up",
      "history": [
        54.8,
        67.8,
        62.8,
        67.5,
        62.0,
        56.9,
        62.9
      ],
      "temperature": {
        "temp_c": -2.1,
        "temp_f": 28.2,
        "normal_c": -3.7,
        "anomaly_c": 1.6,
        "anomaly_f": 2.9
      },
      "skiMarket": true,
      "priorYearHistory": [
        72.0,
        95.1,
        91.1,
        91.1,
        89.9,
        84.3,
        90.5
      ]
    },
    {
      "city": "Minneapolis",
      "region": "MN",
      "country": "usa",
      "cover": 50,
      "depthInches": 7,
      "depthCm": 17.8,
      "trend": "down",
      "history": [
        55.8,
        35.7,
        42.6,
        43.5,
        41.3,
        46.4,
        59.0
      ],
      "temperature": {
        "temp_c": -9.4,
        "temp_f": 15.1,
        "normal_c": -4.4,
        "anomaly_c": -5.0,
        "anomaly_f": -9.0
      },
      "skiMarket": true,
      "priorYearHistory": [
        74.0,
        47.7,
        61.9,
        61.7,
        58.3,
        63.8,
        79.6
      ]
    },
    {
      "city": "Montreal",
      "region": "QC",
      "country": "canada",
      "cover": 40,
      "depthInches": 3.9,
      "depthCm": 10.0,
      "trend": "up",
      "history": [
        28.7,
        53.4,
        35.5,
        39.0,
        45.4,
        48.1,
        43.9
      ],
      "temperature": {
        "temp_c": 2.8,
        "temp_f": 37.0,
        "normal_c": -5.0,
        "anomaly_c": 7.8,
        "anomaly_f": 14.0
      },
      "skiMarket": true,
      "priorYearHistory": [
        42.2,
        65.4,
        52.3,
        54.0,
        55.8,
        65.3,
        60.3
      ]
    },
    {
      "city": "Ottawa",
      "region": "ON",
      "country": "canada",
      "cover": 40,
      "depthInches": 3.9,
      "depthCm": 10.0,
      "trend": "up",
      "history": [
        51.2,
        45.3,
        37.9,
        35.3,
        30.7,
        32.8,
        40.5
      ],
      "temperature": {
        "temp_c": 0.1,
        "temp_f": 32.2,
        "normal_c": null,
        "anomaly_c": null,
        "anomaly_f": null
      },
      "skiMarket": false,
      "priorYearHistory": [
        71.1,
        57.1,
        46.3,
        49.6,
        39.8,
        48.2,
        59.4
      ]
    },
    {
      "city": "Chicago",
      "region": "IL",
      "country": "usa",
      "cover": 25,
      "depthInches": 2,
      "depthCm": 5.1,
      "trend": "stable",
      "history": [
        26.8,
        33.0,
        36.4,
        20.3,
        24.3,
        30.2,
        24.7
      ],
      "temperature": {
        "temp_c": 3.6,
        "temp_f": 38.5,
        "normal_c": -0.0,
        "anomaly_c": 3.6,
        "anomaly_f": 6.5
      },
      "skiMarket": true,
      "priorYearHistory": [
        34.2,
        46.0,
        49.3,
        28.5,
        34.1,
        42.2,
        35.9
      ]
    },
    {
      "city": "Boston",
      "region": "MA",
      "country": "usa",
      "cover": 25,
      "depthInches": 2,
      "depthCm": 5.1,
      "trend": "up",
      "history": [
        24.6,
        13.6,
        26.1,
        29.9,
        33.1,
        31.4,
        32.4
      ],
      "temperature": {
        "temp_c": 3.1,
        "temp_f": 37.6,
        "normal_c": 1.0,
        "anomaly_c": 2.1,
        "anomaly_f": 3.8
      },
      "skiMarket": true,
      "priorYearHistory": [
        30.3,
        18.5,
        31.2,
        36.9,
        39.7,
        43.1,
        45.8
      ]
    },
    {
      "city": "Milwaukee",
      "region": "WI",
      "country": "usa",
      "cover": 25,
      "depthInches": 2,
      "depthCm": 5.1,
      "trend": "stable",
      "history": [
        18.9,
        20.1,
        29.3,
        27.6,
        37.4,
        22.4,
        20.9
      ],
      "temperature": {
        "temp_c": 2.8,
        "temp_f": 37.0,
        "normal_c": -0.9,
        "anomaly_c": 3.7,
        "anomaly_f": 6.7
      },
      "skiMarket": false,
      "priorYearHistory": [
        26.4,
        25.7,
        41.2,
        37.3,
        47.4,
        30.5,
        29.5
      ]
    },
    {
      "city": "New York City",
      "region": "NY",
      "country": "usa",
      "cover": 0,
      "depthInches": 0,
      "depthCm": 0.0,
      "trend": "down",
      "history": [
        15.9,
        11.8,
        0,
        0,
        1.6,
        0,
        5.1
      ],
      "temperature": {
        "temp_c": 5.5,
        "temp_f": 41.9,
        "normal_c": 2.0,
        "anomaly_c": 3.5,
        "anomaly_f": 6.3
      },
      "skiMarket": true,
      "priorYearHistory": [
        20.6,
        17.0,
        0,
        0,
        1.9,
        0,
        6.8
      ]
    },
    {
      "city": "Denver",
      "region": "CO",
      "country": "usa",
      "cover": 0,
      "depthInches": 0,
      "depthCm": 0.0,
      "trend": "stable",
      "history": [
        0,
        4.1,
        15.0,
        5.1,
        10.9,
        0,
        7.4
      ],
      "temperature": {
        "temp_c": 8.2,
        "temp_f": 46.8,
        "normal_c": 1.7,
        "anomaly_c": 6.5,
        "anomaly_f": 11.7
      },
      "skiMarket": true,
      "priorYearHistory": [
        0,
        5.3,
        20.3,
        6.7,
        13.3,
        0,
        9.4
      ]
    },
    {
      "city": "Seattle",
      "region": "WA",
      "country": "usa",
      "cover": 0,
      "depthInches": 0,
      "depthCm": 0.0,
      "trend": "down",
      "history": [
        6.9,
        8.8,
        0,
        5.7,
        0,
        0,
        0
      ],
      "temperature": {
        "temp_c": 8.7,
        "temp_f": 47.7,
        "normal_c": 6.4,
        "anomaly_c": 2.3,
        "anomaly_f": 4.1
      },
      "skiMarket": true,
      "priorYearHistory": [
        8.5,
        12.4,
        0,
        7.4,
        0,
        0,
        0
      ]
    },
    {
      "city": "Detroit",
      "region": "MI",
      "country": "usa",
      "cover": 0,
      "depthInches": 0,
      "depthCm": 0.0,
      "trend": "up",
      "history": [
        0,
        0,
        2.2,
        0,
        8.3,
        0,
        0
      ],
      "temperature": {
        "temp_c": null,
        "temp_f": null,
        "normal_c": 0.8,
        "anomaly_c": null,
        "anomaly_f": null
      },
      "skiMarket": false,
      "priorYearHistory": [
        0,
        0,
        2.9,
        0,
        10.0,
        0,
        0
      ]
    },
    {
      "city": "Salt Lake City",
      "region": "UT",
      "country": "usa",
      "cover": 0,
      "depthInches": 0,
      "depthCm": 0.0,
      "trend": "up",
      "history": [
        0,
        1.1,
        15.1,
        0,
        2.5,
        10.3,
        0
      ],
      "temperature": {
        "temp_c": 7.5,
        "temp_f": 45.5,
        "normal_c": null,
        "anomaly_c": null,
        "anomaly_f": null
      },
      "skiMarket": true,
      "priorYearHistory": [
        0,
        1.3,
        19.2,
        0,
        3.0,
        14.0,
        0
      ]
    },
    {
      "city": "Buffalo",
      "region": "NY",
      "country": "usa",
      "cover": 0,
      "depthInches": 0,
      "depthCm": 0.0,
      "trend": "up",
      "history": [
        8.0,
        16.6,
        0,
        0,
        0,
        3.8,
        0
      ],
      "temperature": {
        "temp_c": 8.4,
        "temp_f": 47.1,
        "normal_c": 0.3,
        "anomaly_c": 8.1,
        "anomaly_f": 14.6
      },
      "skiMarket": false,
      "priorYearHistory": [
        11.5,
        21.8,
        0,
        0,
        0,
        5.0,
        0
      ]
    },
    {
      "city": "Cleveland",
      "region": "OH",
      "country": "usa",
      "cover": 0,
      "depthInches": 0,
      "depthCm": 0.0,
      "trend": "up",
      "history": [
        9.6,
        0,
        6.4,
        0,
        0.8,
        6.8,
        0
      ],
      "temperature": {
        "temp_c": 12.9,
        "temp_f": 55.2,
        "normal_c": 1.9,
        "anomaly_c": 11.0,
        "anomaly_f": 19.8
      },
      "skiMarket": false,
      "priorYearHistory": [
        11.6,
        0,
        8.5,
        0,
        1.1,
        9.6,
        0
      ]
    },
    {
      "city": "Portland",
      "region": "OR",
      "country": "usa",
      "cover": 0,
      "depthInches": 0,
      "depthCm": 0.0,
      "trend": "up",
      "history": [
        0,
        6.5,
        0,
        2.2,
        5.7,
        0.9,
        9.8
      ],
      "temperature": {
        "temp_c": 12.5,
        "temp_f": 54.5,
        "normal_c": 6.7,
        "anomaly_c": 5.8,
        "anomaly_f": 10.4
      },
      "skiMarket": true,
      "priorYearHistory": [
        0,
        9.1,
        0,
        3.2,
        8.2,
        1.3,
        11.8
      ]
    },
    {
      "city": "Toronto",
      "region": "ON",
      "country": "canada",
      "cover": 0,
      "depthInches": 0,
      "depthCm": 0.0,
      "trend": "stable",
      "history": [
        2.8,
        3.4,
        0,
        10.9,
        3.5,
        0,
        0
      ],
      "temperature": {
        "temp_c": null,
        "temp_f": null,
        "normal_c": -0.1,
        "anomaly_c": null,
        "anomaly_f": null
      },
      "skiMarket": true,
      "priorYearHistory": [
        3.4,
        4.7,
        0,
        13.4,
        5.0,
        0,
        0
      ]
    },
    {
      "city": "Vancouver",
      "region": "BC",
      "country": "canada",
      "cover": 0,
      "depthInches": 0,
      "depthCm": 0.0,
      "trend": "stable",
      "history": [
        12.6,
        0,
        0,
        0,
        8.3,
        5.1,
        0.1
      ],
      "temperature": {
        "temp_c": 5.4,
        "temp_f": 41.7,
        "normal_c": 5.7,
        "anomaly_c": -0.3,
        "anomaly_f": -0.5
      },
      "skiMarket": true,
      "priorYearHistory": [
        17.4,
        0,
        0,
        0,
        10.8,
        6.4,
        0.1
      ]
    }
  ]
}