{
  "updated": "2025-12-15 18:05 UTC",
  "data_sources": {
    "usa": "NOHRSC",
    "canada": "Derived (NOHRSC ratio)",
    "rutgers_available": true,
    "copernicus_available": false
  },
  "combined": {
    "cover": 49.4,
    "change": "+4.2%",
    "context": "Approximately 49% of North American land area currently has visible snow cover"
  },
  "usa": {
    "cover": 30.7,
    "change": "+4.2%",
    "areaSqMi": 1165679,
    "areaSqKm": 3019096,
    "avgDepthInches": 4,
    "avgDepthCm": 10.2,
    "priorYearAvgDepthInches": 1.1,
    "priorYearAvgDepthCm": 2.8,
    "history": [
      {
        "date": "2025-11-16",
        "value": 21.5
      },
      {
        "date": "2025-11-17",
        "value": 23.1
      },
      {
        "date": "2025-11-18",
        "value": 22.4
      },
      {
        "date": "2025-11-19",
        "value": 23.4
      },
      {
        "date": "2025-11-20",
        "value": 24.4
      },
      {
        "date": "2025-11-21",
        "value": 25.0
      },
      {
        "date": "2025-11-22",
        "value": 22.0
      },
      {
        "date": "2025-11-23",
        "value": 24.5
      },
      {
        "date": "2025-11-24",
        "value": 24.8
      },
      {
        "date": "2025-11-25",
        "value": 22.0
      },
      {
        "date": "2025-11-26",
        "value": 23.3
      },
      {
        "date": "2025-11-27",
        "value": 23.0
      },
      {
        "date": "2025-11-28",
        "value": 22.8
      },
      {
        "date": "2025-11-29",
        "value": 27.1
      },
      {
        "date": "2025-11-30",
        "value": 28.3
      },
      {
        "date": "2025-12-01",
        "value": 25.1
      },
      {
        "date": "2025-12-02",
        "value": 24.9
      },
      {
        "date": "2025-12-03",
        "value": 26.8
      },
      {
        "date": "2025-12-04",
        "value": 25.5
      },
      {
        "date": "2025-12-05",
        "value": 28.8
      },
      {
        "date": "2025-12-06",
        "value": 30.0
      },
      {
        "date": "2025-12-07",
        "value": 28.6
      },
      {
        "date": "2025-12-08",
        "value": 26.5
      },
      {
        "date": "2025-12-09",
        "value": 30.4
      },
      {
        "date": "2025-12-10",
        "value": 31.1
      },
      {
        "date": "2025-12-11",
        "value": 28.0
      },
      {
        "date": "2025-12-12",
        "value": 31.5
      },
      {
        "date": "2025-12-13",
        "value": 29.5
      },
      {
        "date": "2025-12-14",
        "value": 31.6
      },
      {
        "date": "2025-12-15",
        "value": 28.7
      }
    ],
    "priorYearHistory": [
      {
        "date": "2024-11-16",
        "value": 8.9
      },
      {
        "date": "2024-11-17",
        "value": 11.1
      },
      {
        "date": "2024-11-18",
        "value": 10.5
      },
      {
        "date": "2024-11-19",
        "value": 13.6
      },
      {
        "date": "2024-11-20",
        "value": 14.5
      },
      {
        "date": "2024-11-21",
        "value": 14.8
      },
      {
        "date": "2024-11-22",
        "value": 18.6
      },
      {
        "date": "2024-11-23",
        "value": 15.7
      },
      {
        "date": "2024-11-24",
        "value": 15.6
      },
      {
        "date": "2024-11-25",
        "value": 17.1
      },
      {
        "date": "2024-11-26",
        "value": 19.3
      },
      {
        "date": "2024-11-27",
        "value": 21.7
      },
      {
        "date": "2024-11-28",
        "value": 23.5
      },
      {
        "date": "2024-11-29",
        "value": 25.8
      },
      {
        "date": "2024-11-30",
        "value": 25.4
      },
      {
        "date": "2024-12-01",
        "value": 25.7
      },
      {
        "date": "2024-12-02",
        "value": 25.1
      },
      {
        "date": "2024-12-03",
        "value": 24.4
      },
      {
        "date": "2024-12-04",
        "value": 22.7
      },
      {
        "date": "2024-12-05",
        "value": 21.3
      },
      {
        "date": "2024-12-06",
        "value": 21.5
      },
      {
        "date": "2024-12-07",
        "value": 20.3
      },
      {
        "date": "2024-12-08",
        "value": 17.6
      },
      {
        "date": "2024-12-09",
        "value": 16.8
      },
      {
        "date": "2024-12-10",
        "value": 19.2
      },
      {
        "date": "2024-12-11",
        "value": 19.1
      },
      {
        "date": "2024-12-12",
        "value": 21.7
      },
      {
        "date": "2024-12-13",
        "value": 21.1
      },
      {
        "date": "2024-12-14",
        "value": 21.1
      },
      {
        "date": "2024-12-15",
        "value": 23.4
      }
    ]
  },
  "canada": {
    "cover": 67.7,
    "change": "\u2014",
    "areaSqMi": 2610696,
    "areaSqKm": 6761677,
    "avgDepthInches": 7.5,
    "avgDepthCm": 19,
    "priorYearAvgDepthInches": 2.1,
    "priorYearAvgDepthCm": 5.3,
    "history": [
      {
        "date": "2025-11-16",
        "value": 60.3
      },
      {
        "date": "2025-11-17",
        "value": 64.1
      },
      {
        "date": "2025-11-18",
        "value": 59.6
      },
      {
        "date": "2025-11-19",
        "value": 60.7
      },
      {
        "date": "2025-11-20",
        "value": 64.7
      },
      {
        "date": "2025-11-21",
        "value": 63.8
      },
      {
        "date": "2025-11-22",
        "value": 61.0
      },
      {
        "date": "2025-11-23",
        "value": 62.7
      },
      {
        "date": "2025-11-24",
        "value": 65.3
      },
      {
        "date": "2025-11-25",
        "value": 65.1
      },
      {
        "date": "2025-11-26",
        "value": 63.1
      },
      {
        "date": "2025-11-27",
        "value": 64.7
      },
      {
        "date": "2025-11-28",
        "value": 62.6
      },
      {
        "date": "2025-11-29",
        "value": 62.0
      },
      {
        "date": "2025-11-30",
        "value": 66.6
      },
      {
        "date": "2025-12-01",
        "value": 63.9
      },
      {
        "date": "2025-12-02",
        "value": 67.0
      },
      {
        "date": "2025-12-03",
        "value": 66.6
      },
      {
        "date": "2025-12-04",
        "value": 65.4
      },
      {
        "date": "2025-12-05",
        "value": 65.5
      },
      {
        "date": "2025-12-06",
        "value": 64.6
      },
      {
        "date": "2025-12-07",
        "value": 64.3
      },
      {
        "date": "2025-12-08",
        "value": 68.7
      },
      {
        "date": "2025-12-09",
        "value": 68.0
      },
      {
        "date": "2025-12-10",
        "value": 69.1
      },
      {
        "date": "2025-12-11",
        "value": 66.9
      },
      {
        "date": "2025-12-12",
        "value": 67.3
      },
      {
        "date": "2025-12-13",
        "value": 65.2
      },
      {
        "date": "2025-12-14",
        "value": 68.1
      },
      {
        "date": "2025-12-15",
        "value": 69.8
      }
    ],
    "priorYearHistory": [
      {
        "date": "2024-11-16",
        "value": 25.0
      },
      {
        "date": "2024-11-17",
        "value": 30.8
      },
      {
        "date": "2024-11-18",
        "value": 27.9
      },
      {
        "date": "2024-11-19",
        "value": 35.3
      },
      {
        "date": "2024-11-20",
        "value": 38.4
      },
      {
        "date": "2024-11-21",
        "value": 37.8
      },
      {
        "date": "2024-11-22",
        "value": 51.6
      },
      {
        "date": "2024-11-23",
        "value": 40.2
      },
      {
        "date": "2024-11-24",
        "value": 41.1
      },
      {
        "date": "2024-11-25",
        "value": 50.6
      },
      {
        "date": "2024-11-26",
        "value": 52.3
      },
      {
        "date": "2024-11-27",
        "value": 61.0
      },
      {
        "date": "2024-11-28",
        "value": 64.5
      },
      {
        "date": "2024-11-29",
        "value": 59.0
      },
      {
        "date": "2024-11-30",
        "value": 59.8
      },
      {
        "date": "2024-12-01",
        "value": 65.4
      },
      {
        "date": "2024-12-02",
        "value": 67.5
      },
      {
        "date": "2024-12-03",
        "value": 60.6
      },
      {
        "date": "2024-12-04",
        "value": 58.2
      },
      {
        "date": "2024-12-05",
        "value": 48.4
      },
      {
        "date": "2024-12-06",
        "value": 46.3
      },
      {
        "date": "2024-12-07",
        "value": 45.6
      },
      {
        "date": "2024-12-08",
        "value": 45.6
      },
      {
        "date": "2024-12-09",
        "value": 37.6
      },
      {
        "date": "2024-12-10",
        "value": 42.7
      },
      {
        "date": "2024-12-11",
        "value": 45.6
      },
      {
        "date": "2024-12-12",
        "value": 46.4
      },
      {
        "date": "2024-12-13",
        "value": 46.6
      },
      {
        "date": "2024-12-14",
        "value": 45.5
      },
      {
        "date": "2024-12-15",
        "value": 56.9
      }
    ]
  },
  "metros": [
    {
      "city": "Winnipeg",
      "region": "MB",
      "country": "canada",
      "cover": 65,
      "depthInches": 5.2,
      "depthCm": 13.1,
      "trend": "stable",
      "history": [
        69.9,
        73.9,
        62.2,
        71.9,
        67.0,
        67.0,
        62.5
      ],
      "priorYearHistory": [
        47.8,
        55.4,
        42.2,
        55.9,
        46.0,
        45.5,
        48.4
      ]
    },
    {
      "city": "Quebec City",
      "region": "QC",
      "country": "canada",
      "cover": 65,
      "depthInches": 5.2,
      "depthCm": 13.1,
      "trend": "down",
      "history": [
        62.4,
        77.1,
        52.6,
        54.7,
        70.6,
        67.9,
        68.2
      ],
      "priorYearHistory": [
        42.7,
        58.0,
        39.9,
        41.8,
        53.6,
        47.0,
        54.6
      ]
    },
    {
      "city": "Edmonton",
      "region": "AB",
      "country": "canada",
      "cover": 60,
      "depthInches": 4.9,
      "depthCm": 12.5,
      "trend": "up",
      "history": [
        60.8,
        55.6,
        57.2,
        61.4,
        52.8,
        66.8,
        66.1
      ],
      "priorYearHistory": [
        47.1,
        40.0,
        44.7,
        48.7,
        36.7,
        53.6,
        48.5
      ]
    },
    {
      "city": "Montreal",
      "region": "QC",
      "country": "canada",
      "cover": 50,
      "depthInches": 4.4,
      "depthCm": 11.2,
      "trend": "up",
      "history": [
        43.2,
        44.0,
        56.1,
        65.2,
        53.2,
        48.7,
        44.9
      ],
      "priorYearHistory": [
        31.3,
        30.6,
        40.0,
        48.1,
        41.0,
        36.4,
        31.2
      ]
    },
    {
      "city": "Ottawa",
      "region": "ON",
      "country": "canada",
      "cover": 50,
      "depthInches": 4.4,
      "depthCm": 11.2,
      "trend": "up",
      "history": [
        50.2,
        55.0,
        46.2,
        48.4,
        38.8,
        53.6,
        50.4
      ],
      "priorYearHistory": [
        36.0,
        43.1,
        34.3,
        32.4,
        29.3,
        41.5,
        37.9
      ]
    },
    {
      "city": "New York City",
      "region": "NY",
      "country": "usa",
      "cover": 45,
      "depthInches": 3,
      "depthCm": 7.6,
      "trend": "down",
      "history": [
        44.1,
        33.9,
        48.1,
        52.1,
        43.0,
        44.1,
        37.4
      ],
      "priorYearHistory": [
        34.8,
        27.0,
        33.1,
        39.5,
        30.1,
        29.4,
        25.6
      ]
    },
    {
      "city": "Chicago",
      "region": "IL",
      "country": "usa",
      "cover": 45,
      "depthInches": 3,
      "depthCm": 7.6,
      "trend": "up",
      "history": [
        47.5,
        34.9,
        51.8,
        56.9,
        36.0,
        43.4,
        50.1
      ],
      "priorYearHistory": [
        32.7,
        27.7,
        35.5,
        45.3,
        27.4,
        31.8,
        35.8
      ]
    },
    {
      "city": "Minneapolis",
      "region": "MN",
      "country": "usa",
      "cover": 45,
      "depthInches": 3,
      "depthCm": 7.6,
      "trend": "up",
      "history": [
        47.0,
        58.0,
        41.2,
        41.4,
        40.1,
        43.9,
        42.1
      ],
      "priorYearHistory": [
        37.9,
        43.0,
        32.4,
        31.2,
        27.3,
        31.4,
        29.3
      ]
    },
    {
      "city": "Boston",
      "region": "MA",
      "country": "usa",
      "cover": 45,
      "depthInches": 3,
      "depthCm": 7.6,
      "trend": "up",
      "history": [
        49.5,
        47.9,
        45.7,
        35.4,
        41.2,
        49.7,
        43.6
      ],
      "priorYearHistory": [
        36.9,
        34.2,
        36.1,
        27.0,
        28.8,
        38.5,
        33.7
      ]
    },
    {
      "city": "Detroit",
      "region": "MI",
      "country": "usa",
      "cover": 45,
      "depthInches": 3,
      "depthCm": 7.6,
      "trend": "down",
      "history": [
        53.4,
        59.8,
        47.2,
        30.7,
        51.2,
        55.1,
        54.3
      ],
      "priorYearHistory": [
        41.0,
        39.8,
        31.5,
        24.3,
        40.6,
        42.1,
        40.9
      ]
    },
    {
      "city": "Buffalo",
      "region": "NY",
      "country": "usa",
      "cover": 45,
      "depthInches": 3,
      "depthCm": 7.6,
      "trend": "up",
      "history": [
        58.8,
        49.1,
        53.0,
        57.1,
        41.1,
        39.4,
        47.4
      ],
      "priorYearHistory": [
        42.8,
        34.7,
        41.6,
        39.9,
        30.2,
        28.7,
        32.1
      ]
    },
    {
      "city": "Cleveland",
      "region": "OH",
      "country": "usa",
      "cover": 45,
      "depthInches": 3,
      "depthCm": 7.6,
      "trend": "stable",
      "history": [
        56.5,
        40.6,
        47.4,
        51.6,
        51.9,
        48.0,
        35.2
      ],
      "priorYearHistory": [
        41.4,
        30.0,
        37.5,
        39.8,
        41.3,
        34.2,
        28.0
      ]
    },
    {
      "city": "Milwaukee",
      "region": "WI",
      "country": "usa",
      "cover": 45,
      "depthInches": 3,
      "depthCm": 7.6,
      "trend": "stable",
      "history": [
        62.4,
        35.9,
        35.7,
        44.3,
        39.9,
        55.3,
        47.8
      ],
      "priorYearHistory": [
        45.6,
        27.6,
        24.9,
        33.0,
        28.2,
        41.9,
        32.4
      ]
    },
    {
      "city": "Toronto",
      "region": "ON",
      "country": "canada",
      "cover": 45,
      "depthInches": 4.2,
      "depthCm": 10.6,
      "trend": "up",
      "history": [
        51.5,
        62.3,
        55.2,
        54.7,
        40.5,
        54.1,
        42.1
      ],
      "priorYearHistory": [
        39.1,
        45.0,
        38.2,
        40.3,
        28.9,
        36.3,
        29.7
      ]
    },
    {
      "city": "Salt Lake City",
      "region": "UT",
      "country": "usa",
      "cover": 25,
      "depthInches": 2,
      "depthCm": 5.1,
      "trend": "up",
      "history": [
        36.1,
        39.3,
        36.5,
        34.4,
        18.5,
        18.2,
        34.6
      ],
      "priorYearHistory": [
        24.4,
        29.7,
        28.3,
        25.6,
        13.6,
        13.3,
        25.5
      ]
    },
    {
      "city": "Calgary",
      "region": "AB",
      "country": "canada",
      "cover": 5,
      "depthInches": 0.2,
      "depthCm": 0.6,
      "trend": "up",
      "history": [
        8.2,
        0,
        14.0,
        0,
        11.2,
        8.3,
        3.7
      ],
      "priorYearHistory": [
        6.2,
        0,
        11.3,
        0,
        7.9,
        6.7,
        2.6
      ]
    },
    {
      "city": "Denver",
      "region": "CO",
      "country": "usa",
      "cover": 0,
      "depthInches": 0,
      "depthCm": 0.0,
      "trend": "stable",
      "history": [
        3.0,
        0,
        0,
        0,
        6.5,
        7.8,
        0
      ],
      "priorYearHistory": [
        2.3,
        0,
        0,
        0,
        4.5,
        6.2,
        0
      ]
    },
    {
      "city": "Seattle",
      "region": "WA",
      "country": "usa",
      "cover": 0,
      "depthInches": 0,
      "depthCm": 0.0,
      "trend": "up",
      "history": [
        0,
        0,
        13.1,
        0,
        8.3,
        0,
        0
      ],
      "priorYearHistory": [
        0,
        0,
        9.1,
        0,
        6.4,
        0,
        0
      ]
    },
    {
      "city": "Portland",
      "region": "OR",
      "country": "usa",
      "cover": 0,
      "depthInches": 0,
      "depthCm": 0.0,
      "trend": "stable",
      "history": [
        0,
        0,
        5.5,
        0.1,
        13.0,
        0,
        0
      ],
      "priorYearHistory": [
        0,
        0,
        4.3,
        0.1,
        10.3,
        0,
        0
      ]
    },
    {
      "city": "Vancouver",
      "region": "BC",
      "country": "canada",
      "cover": 0,
      "depthInches": 0,
      "depthCm": 0.0,
      "trend": "up",
      "history": [
        0,
        0.9,
        0,
        0,
        12.7,
        5.3,
        4.2
      ],
      "priorYearHistory": [
        0,
        0.7,
        0,
        0,
        9.0,
        4.0,
        3.2
      ]
    }
  ]
}